test_updating/__init__.py
test_updating/test_updating.py
test_updating-1.dist-info/METADATA
test_updating-1.dist-info/WHEEL
test_updating-1.dist-info/top_level.txt
test_updating-1.dist-info/RECORD
